mkdocs_blog_in/blog.py
mkdocs_blog_in/cli/_utils.py
mkdocs_blog_in/cli/command.py
mkdocs_blog_in/cli/post.py
mkdocs_blog_in/config.py
mkdocs_blog_in/lang/en.yaml
mkdocs_blog_in/lang/pl.yaml
mkdocs_blog_in/modifiers.py
mkdocs_blog_in/parsers.py
mkdocs_blog_in/rendereres.py
mkdocs_blog_in/structures.py
mkdocs_blog_in/templates/posts-list.html
mkdocs_blog_in/translate.py
mkdocs_blog_in-0.3.0.dist-info/entry_points.txt
mkdocs_blog_in-0.3.0.dist-info/LICENSE
mkdocs_blog_in-0.3.0.dist-info/WHEEL
mkdocs_blog_in-0.3.0.dist-info/METADATA
mkdocs_blog_in-0.3.0.dist-info/RECORD
