Metadata-Version: 2.1
Name: mkdocs-blog-in
Version: 0.3.0
Summary: Blogging plugin for MkDocs
Home-page: https://github.com/mkusz/mkdocs-blog-in
License: BSD
Keywords: mkdocs,mkdocs-plugin,blog,blogging
Author: Maciej 'maQ' Kusz
Author-email: maciej.kusz@gmail.com
Requires-Python: >=3.9,<4.0
Classifier: Development Status :: 4 - Beta
Classifier: Environment :: Console
Classifier: Environment :: Web Environment
Classifier: Intended Audience :: Developers
Classifier: License :: OSI Approved :: BSD License
Classifier: License :: Other/Proprietary License
Classifier: Operating System :: OS Independent
Classifier: Programming Language :: Python
Classifier: Programming Language :: Python :: 3
Classifier: Programming Language :: Python :: 3.9
Classifier: Programming Language :: Python :: 3.10
Classifier: Programming Language :: Python :: 3
Classifier: Programming Language :: Python :: 3 :: Only
Classifier: Programming Language :: Python :: 3.10
Classifier: Programming Language :: Python :: 3.11
Classifier: Programming Language :: Python :: 3.9
Classifier: Topic :: Documentation
Classifier: Topic :: Text Processing
Requires-Dist: mkdocs (>=1.4.2,<2.0.0)
Requires-Dist: python-frontmatter (>=1.0.0,<2.0.0)
Project-URL: Bug Tracker, https://github.com/mkusz/mkdocs-blog-in/issues
Project-URL: Documentation, https://mkusz.github.io/mkdocs-blog-in
Project-URL: Repository, https://github.com/mkusz/mkdocs-blog-in
